{"cloud_package_completed_time":"","draft_cloud_capcut_purchase_info":"","draft_cloud_last_action_download":false,"draft_cloud_materials":[],"draft_cloud_purchase_info":"","draft_cloud_template_id":"","draft_cloud_tutorial_info":"","draft_cloud_videocut_purchase_info":"","draft_cover":"E:/JianyingPro Drafts/160D2700-F13A-419F-9A49-5DB70174B9E1/00000_1.png","draft_deeplink_url":"","draft_enterprise_info":{"draft_enterprise_extra":"","draft_enterprise_id":"","draft_enterprise_name":"","enterprise_material":[]},"draft_fold_path":"E:/JianyingPro Drafts/顶顶顶顶 (3)","draft_id":"322B51C0-A263-448d-AA30-F0987F6C6DA5","draft_is_ai_packaging_used":false,"draft_is_ai_shorts":false,"draft_is_ai_translate":false,"draft_is_article_video_draft":false,"draft_is_from_deeplink":"false","draft_is_invisible":false,"draft_materials":[],"draft_materials_copied_info":[],"draft_name":"顶顶顶顶 (3)","draft_new_version":"100.0.0","draft_removable_storage_device":"Unknown","draft_root_path":"E:\\JianyingPro Drafts","draft_segment_extra_info":[],"draft_timeline_materials_size_":512068,"draft_type":"","tm_draft_cloud_completed":"","tm_draft_cloud_modified":0,"tm_draft_create":1755423906229427,"tm_draft_modified":1755423894189,"tm_draft_removed":0,"tm_duration":882000000}